folpy/__init__.py
folpy/examples/__init__.py
folpy/examples/lattices.py
folpy/examples/posets.py
folpy/semantics/__init__.py
folpy/semantics/algebras.py
folpy/semantics/classes.py
folpy/semantics/congruences.py
folpy/semantics/modelfunctions.py
folpy/semantics/models.py
folpy/semantics/morphisms.py
folpy/semantics/theories.py
folpy/syntax/__init__.py
folpy/syntax/formulas.py
folpy/syntax/terms.py
folpy/syntax/types.py
folpy/utils/__init__.py
folpy/utils/functions.py
folpy/utils/misc.py
folpy/utils/minion/__init__.py
folpy/utils/minion/minion
folpy/utils/minion/minion.py
folpy-0.1.2.dist-info/LICENSE
folpy-0.1.2.dist-info/METADATA
folpy-0.1.2.dist-info/WHEEL
folpy-0.1.2.dist-info/top_level.txt
folpy-0.1.2.dist-info/RECORD
