Metadata-Version: 2.1
Name: folpy
Version: 0.1.2
Summary: First Order Logic Python Library
Home-page: https://github.com/gonzigaran/folpy
Author: Gonzalo Zigarán
Author-email: gjzigaran@gmail.com
License: UNKNOWN
Platform: UNKNOWN
Classifier: Programming Language :: Python :: 3
Classifier: License :: OSI Approved :: GNU General Public License v3 (GPLv3)
Classifier: Operating System :: OS Independent
Requires-Python: >=3.6
